rt_dashboard/__init__.py
rt_dashboard/history.py
rt_dashboard/web.py
rt_dashboard/contrib/__init__.py
rt_dashboard/contrib/django/__init__.py
rt_dashboard/contrib/django/templates/rt_dashboard_admin.html
rt_dashboard/static/css/main.css
rt_dashboard/static/img/glyphicons-halflings-white.png
rt_dashboard/static/img/glyphicons-halflings.png
rt_dashboard/static/js/api.js
rt_dashboard/static/js/bootstrap-tooltip.js
rt_dashboard/templates/rt_dashboard/base.html
rt_dashboard/templates/rt_dashboard/dashboard.html
rt_dashboard/templates/rt_dashboard/dashboard.js
rt_dashboard/templates/rt_dashboard/history.html
tests/__init__.py
tests/conftest.py
tests/test_basics.py
rt_dashboard-0.0.8.dist-info/METADATA
rt_dashboard-0.0.8.dist-info/WHEEL
rt_dashboard-0.0.8.dist-info/top_level.txt
rt_dashboard-0.0.8.dist-info/RECORD
